Workbook
Name Rendimento_carteira: 'APP Investimento'!$D$7
Name Valor_Investido: 'APP Investimento'!$D$11
Name Qtd_Anos: 'APP Investimento'!$D$12
Name Taxa_mensal: 'APP Investimento'!$D$13
Name Salari: 'APP Investimento'!$D$6
Name Salario: 'APP Investimento'!$D$6
Name Sugestao_Investimento: 'APP Investimento'!$D$8
Name Patrimonio: 'APP Investimento'!$D$14

Sheet APP Investimento
A2: =_xlfn.DISPIMG("ID_E3EEB9392D764BE3BDFC292EBFFE7961",1) -> =DISPIMG("ID_E3EEB9392D764BE3BDFC292EBFFE7961",1)
B5: CONFIGURAÇÕES
B6: Salário | D6: 5000
B7: Rendimento Carteira | D7: 0.006
B8: Sugestão de Investimento (30%) | D8: =D6*30% -> 1500
B10: INVESTIMENTO MENSAL
B11: Quanto investir por mês? | D11: 500
B12: Por quantos anos? | D12: 5
B13: Taxa de rendimento mensal? | D13: 0.01079
B14: Patrimonio acumulado? | D14: =FV(Taxa_mensal,+Qtd_Anos*12,+Valor_Investido*-1) -> 41888.457
B15: Dividendos mensais? | D15: =Patrimonio*Rendimento_carteira -> 251.33074
B17: CENÁRIOS | D17: Dividendos
A18: 2 | B18: Quanto em 2 anos? | C18: =FV($D$13,$A18*12,$D$11*-1) -> 13613.814 | D18: =C18*Rendimento_carteira -> 81.682882
A19: 5 | B19: Quanto em 5 anos? | C19: =FV($D$13,$A19*12,$D$11*-1) -> 41888.457 | D19: =C19*Rendimento_carteira -> 251.33074
A20: 10 | B20: Quanto em 10 anos? | C20: =FV($D$13,$A20*12,$D$11*-1) -> 121642.11 | D20: =C20*Rendimento_carteira -> 729.85264
A21: 20 | B21: Quanto em 20 anos? | C21: =FV($D$13,$A21*12,$D$11*-1) -> 562599.2 | D21: =C21*Rendimento_carteira -> 3375.5952
A22: 30 | B22: Quanto em 30 anos? | C22: =FV($D$13,$A22*12,$D$11*-1) -> 2161084.8 | D22: =C22*Rendimento_carteira -> 12966.509
B26: PERFIL | C26: Agressivo
B27: VALOR A SER INVESTIDO POR MÊS | C27: =D11 -> 500
B29: TIPO DE FII | C29: Percentual Sugerido | D29: Valores
B30: PAPEL | C30: =VLOOKUP(C26&"-"&B30,'Tabela de apoio'!A:D,4,FALSE()) -> 0.5 | D30: =C27*C$30 -> 250
B31: TIJOLO | C31: =VLOOKUP($C$26&"-"&B31,'Tabela de apoio'!A:D,4,FALSE) -> 0.1 | D31: =C27*C31 -> 50
B32: HIBRIDOS | C32: =VLOOKUP($C$26&"-"&B32,'Tabela de apoio'!A:D,4,FALSE) -> 0.05 | D32: =C27*C32 -> 25
B33: FOFs | C33: =VLOOKUP($C$26&"-"&B33,'Tabela de apoio'!A:D,4,FALSE) -> 0.05 | D33: =C27*C33 -> 25
B34: DESENVOLVIMENTO | C34: =VLOOKUP($C$26&"-"&B34,'Tabela de apoio'!A:D,4,FALSE) -> 0.2 | D34: =C27*C34 -> 100
B35: HOTELARIAS | C35: =VLOOKUP($C$26&"-"&B35,'Tabela de apoio'!A:D,4,FALSE) -> 0.1 | D35: =C27*C35 -> 50
D36: =SUM(D30:D35) -> 500

Sheet Tabela de apoio
A2: CHAVE | B2: PERFIL | C2: TIPO DE FII | D2: %
A3: =B3&"-"&C3 -> Conservador-PAPEL | B3: Conservador | C3: PAPEL | D3: 0.3
A4: =B4&"-"&C4 -> Conservador-TIJOLO | B4: Conservador | C4: TIJOLO | D4: 0.5 | G4: Moderado-TIJOLO | H4: =VLOOKUP(G4,$A:$D,4,FALSE) -> 0.35
A5: =B5&"-"&C5 -> Conservador-HIBRIDOS | B5: Conservador | C5: HIBRIDOS | D5: 0.1
A6: =B6&"-"&C6 -> Conservador-FOFs | B6: Conservador | C6: FOFs | D6: 0.1
A7: =B7&"-"&C7 -> Conservador-DESENVOLVIMENTO | B7: Conservador | C7: DESENVOLVIMENTO | D7: 0
A8: =B8&"-"&C8 -> Conservador-HOTELARIAS | B8: Conservador | C8: HOTELARIAS | D8: 0
A9: =B9&"-"&C9 -> Moderado-PAPEL | B9: Moderado | C9: PAPEL | D9: 0.32
A10: Moderado-TIJOLO | B10: Moderado | C10: TIJOLO | D10: 0.35
A11: =B11&"-"&C11 -> Moderado-HIBRIDOS | B11: Moderado | C11: HIBRIDOS | D11: 0.08
A12: =B12&"-"&C12 -> Moderado-FOFs | B12: Moderado | C12: FOFs | D12: 0.05
A13: =B13&"-"&C13 -> Moderado-DESENVOLVIMENTO | B13: Moderado | C13: DESENVOLVIMENTO | D13: 0.1
A14: =B14&"-"&C14 -> Moderado-HOTELARIAS | B14: Moderado | C14: HOTELARIAS | D14: 0.1
A15: =B15&"-"&C15 -> Agressivo-PAPEL | B15: Agressivo | C15: PAPEL | D15: 0.5
A16: =B16&"-"&C16 -> Agressivo-TIJOLO | B16: Agressivo | C16: TIJOLO | D16: 0.1
A17: =B17&"-"&C17 -> Agressivo-HIBRIDOS | B17: Agressivo | C17: HIBRIDOS | D17: 0.05
A18: =B18&"-"&C18 -> Agressivo-FOFs | B18: Agressivo | C18: FOFs | D18: 0.05
A19: =B19&"-"&C19 -> Agressivo-DESENVOLVIMENTO | B19: Agressivo | C19: DESENVOLVIMENTO | D19: 0.2
A20: =B20&"-"&C20 -> Agressivo-HOTELARIAS | B20: Agressivo | C20: HOTELARIAS | D20: 0.1
